openairbearing/__init__.py
openairbearing/bearings.py
openairbearing/config.py
openairbearing/plots.py
openairbearing/solvers.py
openairbearing/utils.py
openairbearing/app/app.py
openairbearing/app/callbacks.py
openairbearing/app/layouts.py
openairbearing-0.1.8.dist-info/licenses/LICENSE
openairbearing-0.1.8.dist-info/METADATA
openairbearing-0.1.8.dist-info/WHEEL
openairbearing-0.1.8.dist-info/entry_points.txt
openairbearing-0.1.8.dist-info/top_level.txt
openairbearing-0.1.8.dist-info/RECORD
