Metadata-Version: 2.4
Name: openairbearing
Version: 0.1.8
Summary: A Python package for externally pressurized air bearing analysis.
Author-email: Mikael Miettinen <mikael.miettinen@iki.fi>
License: MIT License
Project-URL: Homepage, https://github.com/Aalto-Arotor/openAirBearing
Project-URL: Online demo, https://www.openairbearing.com
Classifier: Programming Language :: Python :: 3
Classifier: License :: OSI Approved :: MIT License
Classifier: Operating System :: OS Independent
Requires-Python: >=3.10
License-File: LICENSE
Requires-Dist: dash<3.0.0,>=2.18.2
Requires-Dist: numpy<3.0.0,>=2.2.3
Requires-Dist: plotly<7.0.0,>=6.0.0
Requires-Dist: scipy<2.0.0,>=1.7.0
Dynamic: license-file
